ddisasm/py.typed
ddisasm/__init__.py
ddisasm/__main__.py
ddisasm/ddisasm
ddisasm/version.py
ddisasm/.libs/libgtirb_pprinter.so.2
ddisasm/.libs/libcapstone.so.5
ddisasm/.libs/libgtirb.so.2.3.0
ddisasm/.libs/libgtirb_layout.so.2
ddisasm-1.9.2.dist-info/METADATA
ddisasm-1.9.2.dist-info/entry_points.txt
ddisasm-1.9.2.dist-info/top_level.txt
ddisasm-1.9.2.dist-info/WHEEL
ddisasm-1.9.2.dist-info/RECORD
ddisasm.libs/libgomp-f7e03b3e.so.1.0.0
