Metadata-Version: 2.1
Name: ddisasm
Version: 1.9.2
Summary: A fast and accurate disassembler
Home-page: https://github.com/grammatech/ddisasm
Author: GrammaTech, Inc.
Author-email: gtirb@grammatech.com
License: AGPL-3.0
Keywords: reverse-engineering,disassembler,binary-analysis,intermediate-representation,binary-rewriting,gtirb
Classifier: License :: OSI Approved :: GNU Affero General Public License v3
Classifier: Topic :: Software Development :: Disassemblers
Classifier: Development Status :: 5 - Production/Stable
Classifier: Intended Audience :: Developers
Classifier: Intended Audience :: System Administrators
Classifier: Operating System :: Microsoft :: Windows
Classifier: Operating System :: POSIX
Requires-Python: >=3.6
Requires-Dist: gtirb (==2.3.0)
Requires-Dist: importlib-resources ; python_version < "3.9"
